CHANGES
MANIFEST.in
README.md
pytest.ini
runtests.py
setup.py
importmagic/__init__.py
importmagic/conftest.py
importmagic/importer.py
importmagic/importer_test.py
importmagic/index.py
importmagic/index_test.py
importmagic/six.py
importmagic/symbols.py
importmagic/symbols_test.py
importmagic/test_index.json
importmagic/util.py
importmagic.egg-info/PKG-INFO
importmagic.egg-info/SOURCES.txt
importmagic.egg-info/dependency_links.txt
importmagic.egg-info/requires.txt
importmagic.egg-info/top_level.txt