Metadata-Version: 1.1
Name: importmagic
Version: 0.1.6
Summary: Python Import Magic - automagically add, remove and manage imports
Home-page: http://github.com/alecthomas/importmagic
Author: Alec Thomas
Author-email: alec@swapoff.org
License: BSD
Download-URL: http://pypi.python.org/pypi/importmagic
Platform: any
